compas_xr/__init__.py
compas_xr/__main__.py
compas_xr/dependencies/Firebase.Auth.dll
compas_xr/dependencies/Firebase.Auth.xml
compas_xr/dependencies/Firebase.Storage.dll
compas_xr/dependencies/Firebase.dll
compas_xr/dependencies/Firebase.xml
compas_xr/dependencies/LiteDB.dll
compas_xr/dependencies/LiteDB.xml
compas_xr/dependencies/Newtonsoft.Json.dll
compas_xr/dependencies/Newtonsoft.Json.xml
compas_xr/dependencies/System.Reactive.dll
compas_xr/dependencies/System.Reactive.xml
compas_xr/ghpython/__init__.py
compas_xr/ghpython/app_settings.py
compas_xr/ghpython/firebase_config.py
compas_xr/ghpython/options.py
compas_xr/ghpython/trajectory_manager.py
compas_xr/ghpython/components/___init__.py
compas_xr/ghpython/components/Cx_AppSettings/code.py
compas_xr/ghpython/components/Cx_AppSettings/icon.png
compas_xr/ghpython/components/Cx_AppSettings/metadata.json
compas_xr/ghpython/components/Cx_Firebase_Config/code.py
compas_xr/ghpython/components/Cx_Firebase_Config/icon.png
compas_xr/ghpython/components/Cx_Firebase_Config/metadata.json
compas_xr/ghpython/components/Cx_GetTrajectoryRequest/code.py
compas_xr/ghpython/components/Cx_GetTrajectoryRequest/icon.png
compas_xr/ghpython/components/Cx_GetTrajectoryRequest/metadata.json
compas_xr/ghpython/components/Cx_MqttTrajectoryResult/code.py
compas_xr/ghpython/components/Cx_MqttTrajectoryResult/icon.png
compas_xr/ghpython/components/Cx_MqttTrajectoryResult/metadata.json
compas_xr/ghpython/components/Cx_PlanningServiceResponse/code.py
compas_xr/ghpython/components/Cx_PlanningServiceResponse/icon.png
compas_xr/ghpython/components/Cx_PlanningServiceResponse/metadata.json
compas_xr/ghpython/components/Cx_SendTrajectory/code.py
compas_xr/ghpython/components/Cx_SendTrajectory/icon.png
compas_xr/ghpython/components/Cx_SendTrajectory/metadata.json
compas_xr/ghpython/components/Cx_XrOptions/code.py
compas_xr/ghpython/components/Cx_XrOptions/icon.png
compas_xr/ghpython/components/Cx_XrOptions/metadata.json
compas_xr-1.0.0.dist-info/AUTHORS.md
compas_xr-1.0.0.dist-info/LICENSE
compas_xr-1.0.0.dist-info/METADATA
compas_xr-1.0.0.dist-info/WHEEL
compas_xr-1.0.0.dist-info/top_level.txt
compas_xr-1.0.0.dist-info/RECORD
