Metadata-Version: 2.1
Name: compas_xr
Version: 1.0.0
Summary: COMPAS XR streamlines extended reality workflows to ease the implementation of human-machine collaborative applications in architectural research and educational environments.
Author-email: Joseph Kenny <kenny@arch.ethz.ch>, Daniela Mitterberger <mitterberger@princeton.edu>
License: MIT License
Project-URL: Homepage, https://github.com/gramaziokohler/compas_xr
Project-URL: Documentation, https://gramaziokohler.github.io/compas_xr/
Project-URL: Repository, https://github.com/gramaziokohler/compas_xr.git
Project-URL: Changelog, https://github.com/gramaziokohler/compas_xr/blob/main/CHANGELOG.md
Project-URL: Issues, https://github.com/gramaziokohler/compas_xr/issues
Project-URL: Forum, https://forum.compas-framework.org/
Keywords: compas,xr,aec,robotic,human-machine
Classifier: Development Status :: 4 - Beta
Classifier: Topic :: Scientific/Engineering
Classifier: Operating System :: Unix
Classifier: Operating System :: POSIX
Classifier: Operating System :: Microsoft :: Windows
Classifier: Programming Language :: Python
Classifier: Programming Language :: Python :: 3
Classifier: Programming Language :: Python :: 3.9
Classifier: Programming Language :: Python :: 3.10
Classifier: Programming Language :: Python :: 3.11
Requires-Python: >=3.9
License-File: LICENSE
License-File: AUTHORS.md
Requires-Dist: numpy <2,>=1.15.4
Requires-Dist: compas <3,>=2.0.4
Requires-Dist: compas-timber ~=0.7.0
Requires-Dist: compas-eve <2,>=1
Requires-Dist: compas-fab <2,>=1.0.2
Requires-Dist: pyrebase4 >=4.7.1
Provides-Extra: dev
Requires-Dist: attrs >=17.4 ; extra == 'dev'
Requires-Dist: black >=22.12.0 ; extra == 'dev'
Requires-Dist: bump-my-version ; extra == 'dev'
Requires-Dist: compas-invocations2 ; extra == 'dev'
Requires-Dist: invoke >=0.14 ; extra == 'dev'
Requires-Dist: ruff ; extra == 'dev'
Requires-Dist: sphinx-compas2-theme ; extra == 'dev'
Requires-Dist: twine ; extra == 'dev'
Requires-Dist: wheel ; extra == 'dev'
